plapperi/__init__.py
plapperi/client.py
plapperi/version.py
plapperi/errors/__init__.py
plapperi/errors/api_error.py
plapperi/errors/timeout_error.py
plapperi/errors/unauthorized_error.py
plapperi/operations/base_client.py
plapperi/operations/synthetization/__init__.py
plapperi/operations/synthetization/client.py
plapperi/operations/translation/__init__.py
plapperi/operations/translation/client.py
plapperi/types/__init__.py
plapperi/types/dialect.py
plapperi/types/job.py
plapperi/types/synthetization.py
plapperi/types/translation.py
plapperi-0.0.2.dist-info/METADATA
plapperi-0.0.2.dist-info/WHEEL
plapperi-0.0.2.dist-info/licenses/LICENSE
plapperi-0.0.2.dist-info/RECORD
